war_thunder_plane_info/__init__.py
war_thunder_plane_info/wt.py
war_thunder_plane_info-0.0.5.dist-info/METADATA
war_thunder_plane_info-0.0.5.dist-info/WHEEL
war_thunder_plane_info-0.0.5.dist-info/licenses/LICENSE
war_thunder_plane_info-0.0.5.dist-info/RECORD
