Metadata-Version: 2.4
Name: war-thunder-plane-info
Version: 0.0.5
Summary: Получение информации о самолетах
Project-URL: Homepage, https://github.com/Sergey-Titkov/war_thunder_plane_info
Project-URL: Issues, https://github.com/Sergey-Titkov/war_thunder_plane_info/issues
Project-URL: Discord, https://discord.gg/ktstFYtyUR
Author-email: Sergey Titkov <srg.titkov@gmail.com>
License-Expression: MIT
License-File: LICENSE
Classifier: Operating System :: OS Independent
Classifier: Programming Language :: Python :: 3
Requires-Python: >=3.13
